LICENSE
MANIFEST.in
README.md
requirements.txt
setup.py
vulcanai/__init__.py
vulcanai/logging.conf
vulcanai.egg-info/PKG-INFO
vulcanai.egg-info/SOURCES.txt
vulcanai.egg-info/dependency_links.txt
vulcanai.egg-info/requires.txt
vulcanai.egg-info/top_level.txt
vulcanai/datasets/__init__.py
vulcanai/datasets/fashion.py
vulcanai/datasets/multidataset.py
vulcanai/datasets/tabular_data_utils.py
vulcanai/datasets/utils.py
vulcanai/models/__init__.py
vulcanai/models/basenetwork.py
vulcanai/models/cnn.py
vulcanai/models/dnn.py
vulcanai/models/ensemble.py
vulcanai/models/layers.py
vulcanai/models/metrics.py
vulcanai/models/utils.py
vulcanai/plotters/__init__.py
vulcanai/plotters/utils.py
vulcanai/plotters/visualization.py
vulcanai/tests/datasets/test_tabulardataset.py
vulcanai/tests/models/__init__.py
vulcanai/tests/models/conftest.py
vulcanai/tests/models/test_basenetwork.py
vulcanai/tests/models/test_cnn.py
vulcanai/tests/models/test_device.py
vulcanai/tests/models/test_dnn.py
vulcanai/tests/models/test_ensemble.py
vulcanai/tests/models/test_layers.py
vulcanai/tests/models/test_metrics.py
vulcanai/tests/models/test_utils.py
vulcanai/tests/plotters/test_visualization.py