Metadata-Version: 2.1
Name: vulcanai
Version: 1.0.8
Summary: A high-level framework built on top of Pytorch using added functionality from Scikit-learn to provide all of the tools needed for visualizing and processing high-dimensional data, modular neural networks, and model evaluation
Home-page: https://github.com/Aifred-Health/Vulcan
Author: Robert Fratila, Priyatharsan Rajasekar, Caitrin Armstrong, Joseph Mehltretter, Sneha Desai
Author-email: robertfratila10@gmail.com
License: UNKNOWN
Keywords: deep learning machine learning development framework
Platform: UNKNOWN
Classifier: Development Status :: 3 - Alpha
Classifier: Intended Audience :: Developers
Classifier: Intended Audience :: Science/Research
Classifier: Intended Audience :: Education
Classifier: Topic :: Software Development :: Build Tools
Classifier: Programming Language :: Python :: 3.6
Classifier: Operating System :: Unix
Classifier: Operating System :: POSIX :: Linux
Classifier: Topic :: Scientific/Engineering :: Artificial Intelligence
Provides-Extra: testing
Provides-Extra: docs
